{
  "$schema": "https://vega.github.io/schema/vega-lite/v6.1.0.json",
  "config": {
    "view": {
      "continuousHeight": 300,
      "continuousWidth": 300
    }
  },
  "data": {
    "name": "data-4ea58b24df7fd62eb1eec8e8b6df5151"
  },
  "datasets": {
    "data-4ea58b24df7fd62eb1eec8e8b6df5151": [
      {
        "deployment": "6089_old_gps2_diq202504-202509",
        "deployment_order": 18,
        "event_index": 0,
        "hour_of_day": 13.866388888888888,
        "media_type": "jpeg",
        "timestamp": "2024-09-07T13:51:59"
      },
      {
        "deployment": "6089_old_gps2_diq202504-202509",
        "deployment_order": 18,
        "event_index": 1,
        "hour_of_day": 13.871666666666668,
        "media_type": "mp4",
        "timestamp": "2024-09-07T13:52:18"
      },
      {
        "deployment": "6089_old_gps2_diq202504-202509",
        "deployment_order": 18,
        "event_index": 2,
        "hour_of_day": 11.060555555555556,
        "media_type": "jpeg",
        "timestamp": "2024-09-09T11:03:38"
      },
      {
        "deployment": "6089_old_gps2_diq202504-202509",
        "deployment_order": 18,
        "event_index": 3,
        "hour_of_day": 11.060833333333335,
        "media_type": "jpeg",
        "timestamp": "2024-09-09T11:03:39"
      },
      {
        "deployment": "6089_old_gps2_diq202504-202509",
        "deployment_order": 18,
        "event_index": 4,
        "hour_of_day": 11.066111111111113,
        "media_type": "mp4",
        "timestamp": "2024-09-09T11:03:58"
      },
      {
        "deployment": "6089_old_gps2_diq202504-202509",
        "deployment_order": 18,
        "event_index": 5,
        "hour_of_day": 13.332777777777778,
        "media_type": "jpeg",
        "timestamp": "2024-09-09T13:19:58"
      },
      {
        "deployment": "6089_old_gps2_diq202504-202509",
        "deployment_order": 18,
        "event_index": 6,
        "hour_of_day": 13.338333333333335,
        "media_type": "mp4",
        "timestamp": "2024-09-09T13:20:18"
      },
      {
        "deployment": "6089_old_gps2_diq202504-202509",
        "deployment_order": 18,
        "event_index": 7,
        "hour_of_day": 17.438055555555557,
        "media_type": "jpeg",
        "timestamp": "2024-09-10T17:26:17"
      },
      {
        "deployment": "6089_old_gps2_diq202504-202509",
        "deployment_order": 18,
        "event_index": 8,
        "hour_of_day": 17.438333333333333,
        "media_type": "jpeg",
        "timestamp": "2024-09-10T17:26:18"
      },
      {
        "deployment": "6089_old_gps2_diq202504-202509",
        "deployment_order": 18,
        "event_index": 9,
        "hour_of_day": 17.44388888888889,
        "media_type": "mp4",
        "timestamp": "2024-09-10T17:26:38"
      },
      {
        "deployment": "6089_old_gps2_diq202504-202509",
        "deployment_order": 18,
        "event_index": 10,
        "hour_of_day": 2.4594444444444448,
        "media_type": "jpeg",
        "timestamp": "2024-09-12T02:27:34"
      },
      {
        "deployment": "6089_old_gps2_diq202504-202509",
        "deployment_order": 18,
        "event_index": 11,
        "hour_of_day": 2.4597222222222226,
        "media_type": "jpeg",
        "timestamp": "2024-09-12T02:27:35"
      },
      {
        "deployment": "6089_old_gps2_diq202504-202509",
        "deployment_order": 18,
        "event_index": 12,
        "hour_of_day": 2.4650000000000003,
        "media_type": "mp4",
        "timestamp": "2024-09-12T02:27:54"
      },
      {
        "deployment": "6089_old_gps2_diq202504-202509",
        "deployment_order": 18,
        "event_index": 13,
        "hour_of_day": 19.07638888888889,
        "media_type": "jpeg",
        "timestamp": "2024-09-12T19:04:35"
      },
      {
        "deployment": "6089_old_gps2_diq202504-202509",
        "deployment_order": 18,
        "event_index": 14,
        "hour_of_day": 19.076666666666668,
        "media_type": "jpeg",
        "timestamp": "2024-09-12T19:04:36"
      },
      {
        "deployment": "6089_old_gps2_diq202504-202509",
        "deployment_order": 18,
        "event_index": 15,
        "hour_of_day": 19.081666666666667,
        "media_type": "mp4",
        "timestamp": "2024-09-12T19:04:54"
      },
      {
        "deployment": "6089_old_gps2_diq202504-202509",
        "deployment_order": 18,
        "event_index": 16,
        "hour_of_day": 12.349166666666667,
        "media_type": "jpeg",
        "timestamp": "2024-09-13T12:20:57"
      },
      {
        "deployment": "6089_old_gps2_diq202504-202509",
        "deployment_order": 18,
        "event_index": 17,
        "hour_of_day": 12.358055555555556,
        "media_type": "jpeg",
        "timestamp": "2024-09-13T12:21:29"
      },
      {
        "deployment": "6089_old_gps2_diq202504-202509",
        "deployment_order": 18,
        "event_index": 18,
        "hour_of_day": 8.774166666666668,
        "media_type": "jpeg",
        "timestamp": "2024-09-14T08:46:27"
      },
      {
        "deployment": "6089_old_gps2_diq202504-202509",
        "deployment_order": 18,
        "event_index": 19,
        "hour_of_day": 8.774444444444445,
        "media_type": "jpeg",
        "timestamp": "2024-09-14T08:46:28"
      },
      {
        "deployment": "6089_old_gps2_diq202504-202509",
        "deployment_order": 18,
        "event_index": 20,
        "hour_of_day": 8.779444444444445,
        "media_type": "mp4",
        "timestamp": "2024-09-14T08:46:46"
      },
      {
        "deployment": "6089_old_gps2_diq202504-202509",
        "deployment_order": 18,
        "event_index": 21,
        "hour_of_day": 8.826944444444445,
        "media_type": "jpeg",
        "timestamp": "2024-09-14T08:49:37"
      },
      {
        "deployment": "6089_old_gps2_diq202504-202509",
        "deployment_order": 18,
        "event_index": 22,
        "hour_of_day": 8.827222222222222,
        "media_type": "jpeg",
        "timestamp": "2024-09-14T08:49:38"
      },
      {
        "deployment": "6089_old_gps2_diq202504-202509",
        "deployment_order": 18,
        "event_index": 23,
        "hour_of_day": 8.832222222222223,
        "media_type": "mp4",
        "timestamp": "2024-09-14T08:49:56"
      },
      {
        "deployment": "6089_old_gps2_diq202504-202509",
        "deployment_order": 18,
        "event_index": 24,
        "hour_of_day": 8.883333333333333,
        "media_type": "jpeg",
        "timestamp": "2024-09-14T08:53:00"
      },
      {
        "deployment": "6089_old_gps2_diq202504-202509",
        "deployment_order": 18,
        "event_index": 25,
        "hour_of_day": 8.88361111111111,
        "media_type": "jpeg",
        "timestamp": "2024-09-14T08:53:01"
      },
      {
        "deployment": "6089_old_gps2_diq202504-202509",
        "deployment_order": 18,
        "event_index": 26,
        "hour_of_day": 9.46361111111111,
        "media_type": "jpeg",
        "timestamp": "2024-09-14T09:27:49"
      },
      {
        "deployment": "6089_old_gps2_diq202504-202509",
        "deployment_order": 18,
        "event_index": 27,
        "hour_of_day": 9.513333333333334,
        "media_type": "jpeg",
        "timestamp": "2024-09-14T09:30:48"
      },
      {
        "deployment": "6089_old_gps2_diq202504-202509",
        "deployment_order": 18,
        "event_index": 28,
        "hour_of_day": 19.728888888888886,
        "media_type": "jpeg",
        "timestamp": "2024-09-14T19:43:44"
      },
      {
        "deployment": "6089_old_gps2_diq202504-202509",
        "deployment_order": 18,
        "event_index": 29,
        "hour_of_day": 19.729166666666664,
        "media_type": "jpeg",
        "timestamp": "2024-09-14T19:43:45"
      },
      {
        "deployment": "6089_old_gps2_diq202504-202509",
        "deployment_order": 18,
        "event_index": 30,
        "hour_of_day": 19.734444444444446,
        "media_type": "mp4",
        "timestamp": "2024-09-14T19:44:04"
      },
      {
        "deployment": "6089_old_gps2_diq202504-202509",
        "deployment_order": 18,
        "event_index": 31,
        "hour_of_day": 8.942222222222222,
        "media_type": "jpeg",
        "timestamp": "2024-09-15T08:56:32"
      },
      {
        "deployment": "6089_old_gps2_diq202504-202509",
        "deployment_order": 18,
        "event_index": 32,
        "hour_of_day": 8.9425,
        "media_type": "jpeg",
        "timestamp": "2024-09-15T08:56:33"
      },
      {
        "deployment": "6089_old_gps2_diq202504-202509",
        "deployment_order": 18,
        "event_index": 33,
        "hour_of_day": 8.947777777777778,
        "media_type": "mp4",
        "timestamp": "2024-09-15T08:56:52"
      },
      {
        "deployment": "6089_old_gps2_diq202504-202509",
        "deployment_order": 18,
        "event_index": 34,
        "hour_of_day": 12.598333333333334,
        "media_type": "jpeg",
        "timestamp": "2024-09-15T12:35:54"
      },
      {
        "deployment": "6089_old_gps2_diq202504-202509",
        "deployment_order": 18,
        "event_index": 35,
        "hour_of_day": 12.714722222222221,
        "media_type": "jpeg",
        "timestamp": "2024-09-15T12:42:53"
      },
      {
        "deployment": "6089_old_gps2_diq202504-202509",
        "deployment_order": 18,
        "event_index": 36,
        "hour_of_day": 12.715,
        "media_type": "jpeg",
        "timestamp": "2024-09-15T12:42:54"
      },
      {
        "deployment": "6089_old_gps2_diq202504-202509",
        "deployment_order": 18,
        "event_index": 37,
        "hour_of_day": 12.72,
        "media_type": "mp4",
        "timestamp": "2024-09-15T12:43:12"
      },
      {
        "deployment": "6089_old_gps2_diq202504-202509",
        "deployment_order": 18,
        "event_index": 38,
        "hour_of_day": 12.722777777777777,
        "media_type": "jpeg",
        "timestamp": "2024-09-15T12:43:22"
      },
      {
        "deployment": "6089_old_gps2_diq202504-202509",
        "deployment_order": 18,
        "event_index": 39,
        "hour_of_day": 12.723055555555556,
        "media_type": "jpeg",
        "timestamp": "2024-09-15T12:43:23"
      },
      {
        "deployment": "6089_old_gps2_diq202504-202509",
        "deployment_order": 18,
        "event_index": 40,
        "hour_of_day": 12.728333333333333,
        "media_type": "mp4",
        "timestamp": "2024-09-15T12:43:42"
      },
      {
        "deployment": "6089_old_gps2_diq202504-202509",
        "deployment_order": 18,
        "event_index": 41,
        "hour_of_day": 18.158055555555553,
        "media_type": "jpeg",
        "timestamp": "2024-09-15T18:09:29"
      },
      {
        "deployment": "6089_old_gps2_diq202504-202509",
        "deployment_order": 18,
        "event_index": 42,
        "hour_of_day": 3.901388888888889,
        "media_type": "jpeg",
        "timestamp": "2024-09-17T03:54:05"
      },
      {
        "deployment": "6089_old_gps2_diq202504-202509",
        "deployment_order": 18,
        "event_index": 43,
        "hour_of_day": 3.9016666666666664,
        "media_type": "jpeg",
        "timestamp": "2024-09-17T03:54:06"
      },
      {
        "deployment": "6089_old_gps2_diq202504-202509",
        "deployment_order": 18,
        "event_index": 44,
        "hour_of_day": 3.9119444444444444,
        "media_type": "jpeg",
        "timestamp": "2024-09-17T03:54:43"
      },
      {
        "deployment": "6089_old_gps2_diq202504-202509",
        "deployment_order": 18,
        "event_index": 45,
        "hour_of_day": 3.917222222222222,
        "media_type": "mp4",
        "timestamp": "2024-09-17T03:55:02"
      },
      {
        "deployment": "6089_old_gps2_diq202504-202509",
        "deployment_order": 18,
        "event_index": 46,
        "hour_of_day": 9.75611111111111,
        "media_type": "jpeg",
        "timestamp": "2024-09-17T09:45:22"
      },
      {
        "deployment": "6089_old_gps2_diq202504-202509",
        "deployment_order": 18,
        "event_index": 47,
        "hour_of_day": 9.756388888888889,
        "media_type": "jpeg",
        "timestamp": "2024-09-17T09:45:23"
      },
      {
        "deployment": "6089_old_gps2_diq202504-202509",
        "deployment_order": 18,
        "event_index": 48,
        "hour_of_day": 9.761666666666667,
        "media_type": "mp4",
        "timestamp": "2024-09-17T09:45:42"
      },
      {
        "deployment": "6089_old_gps2_diq202504-202509",
        "deployment_order": 18,
        "event_index": 49,
        "hour_of_day": 9.358888888888888,
        "media_type": "jpeg",
        "timestamp": "2024-09-18T09:21:32"
      },
      {
        "deployment": "6089_old_gps2_diq202504-202509",
        "deployment_order": 18,
        "event_index": 50,
        "hour_of_day": 9.359166666666667,
        "media_type": "jpeg",
        "timestamp": "2024-09-18T09:21:33"
      },
      {
        "deployment": "6089_old_gps2_diq202504-202509",
        "deployment_order": 18,
        "event_index": 51,
        "hour_of_day": 10.923888888888888,
        "media_type": "jpeg",
        "timestamp": "2024-09-18T10:55:26"
      },
      {
        "deployment": "6089_old_gps2_diq202504-202509",
        "deployment_order": 18,
        "event_index": 52,
        "hour_of_day": 10.928888888888888,
        "media_type": "mp4",
        "timestamp": "2024-09-18T10:55:44"
      },
      {
        "deployment": "6089_old_gps2_diq202504-202509",
        "deployment_order": 18,
        "event_index": 53,
        "hour_of_day": 11.041944444444445,
        "media_type": "jpeg",
        "timestamp": "2024-09-18T11:02:31"
      },
      {
        "deployment": "6089_old_gps2_diq202504-202509",
        "deployment_order": 18,
        "event_index": 54,
        "hour_of_day": 11.042222222222222,
        "media_type": "jpeg",
        "timestamp": "2024-09-18T11:02:32"
      },
      {
        "deployment": "6089_old_gps2_diq202504-202509",
        "deployment_order": 18,
        "event_index": 55,
        "hour_of_day": 11.047222222222222,
        "media_type": "mp4",
        "timestamp": "2024-09-18T11:02:50"
      },
      {
        "deployment": "6089_old_gps2_diq202504-202509",
        "deployment_order": 18,
        "event_index": 56,
        "hour_of_day": 18.220555555555553,
        "media_type": "jpeg",
        "timestamp": "2024-09-19T18:13:14"
      },
      {
        "deployment": "6089_old_gps2_diq202504-202509",
        "deployment_order": 18,
        "event_index": 57,
        "hour_of_day": 18.22083333333333,
        "media_type": "jpeg",
        "timestamp": "2024-09-19T18:13:15"
      },
      {
        "deployment": "6089_old_gps2_diq202504-202509",
        "deployment_order": 18,
        "event_index": 58,
        "hour_of_day": 18.22611111111111,
        "media_type": "mp4",
        "timestamp": "2024-09-19T18:13:34"
      },
      {
        "deployment": "6089_old_gps2_diq202504-202509",
        "deployment_order": 18,
        "event_index": 59,
        "hour_of_day": 12.6725,
        "media_type": "jpeg",
        "timestamp": "2024-09-21T12:40:21"
      },
      {
        "deployment": "6089_old_gps2_diq202504-202509",
        "deployment_order": 18,
        "event_index": 60,
        "hour_of_day": 12.672777777777776,
        "media_type": "jpeg",
        "timestamp": "2024-09-21T12:40:22"
      },
      {
        "deployment": "6089_old_gps2_diq202504-202509",
        "deployment_order": 18,
        "event_index": 61,
        "hour_of_day": 12.677777777777777,
        "media_type": "mp4",
        "timestamp": "2024-09-21T12:40:40"
      },
      {
        "deployment": "6089_old_gps2_diq202504-202509",
        "deployment_order": 18,
        "event_index": 62,
        "hour_of_day": 12.695833333333333,
        "media_type": "jpeg",
        "timestamp": "2024-09-21T12:41:45"
      },
      {
        "deployment": "6089_old_gps2_diq202504-202509",
        "deployment_order": 18,
        "event_index": 63,
        "hour_of_day": 12.696111111111112,
        "media_type": "jpeg",
        "timestamp": "2024-09-21T12:41:46"
      },
      {
        "deployment": "6089_old_gps2_diq202504-202509",
        "deployment_order": 18,
        "event_index": 64,
        "hour_of_day": 12.70111111111111,
        "media_type": "mp4",
        "timestamp": "2024-09-21T12:42:04"
      },
      {
        "deployment": "6089_old_gps2_diq202504-202509",
        "deployment_order": 18,
        "event_index": 65,
        "hour_of_day": 21.077222222222222,
        "media_type": "jpeg",
        "timestamp": "2024-09-21T21:04:38"
      },
      {
        "deployment": "6089_old_gps2_diq202504-202509",
        "deployment_order": 18,
        "event_index": 66,
        "hour_of_day": 21.08222222222222,
        "media_type": "mp4",
        "timestamp": "2024-09-21T21:04:56"
      },
      {
        "deployment": "6089_old_gps2_diq202504-202509",
        "deployment_order": 18,
        "event_index": 67,
        "hour_of_day": 12.773888888888889,
        "media_type": "mp4",
        "timestamp": "2024-09-22T12:46:26"
      },
      {
        "deployment": "6089_old_gps2_diq202504-202509",
        "deployment_order": 18,
        "event_index": 68,
        "hour_of_day": 15.433333333333334,
        "media_type": "jpeg",
        "timestamp": "2024-09-22T15:26:00"
      },
      {
        "deployment": "6089_old_gps2_diq202504-202509",
        "deployment_order": 18,
        "event_index": 69,
        "hour_of_day": 15.43361111111111,
        "media_type": "jpeg",
        "timestamp": "2024-09-22T15:26:01"
      },
      {
        "deployment": "6089_old_gps2_diq202504-202509",
        "deployment_order": 18,
        "event_index": 70,
        "hour_of_day": 15.43888888888889,
        "media_type": "mp4",
        "timestamp": "2024-09-22T15:26:20"
      },
      {
        "deployment": "6089_old_gps2_diq202504-202509",
        "deployment_order": 18,
        "event_index": 71,
        "hour_of_day": 15.450277777777776,
        "media_type": "jpeg",
        "timestamp": "2024-09-22T15:27:01"
      },
      {
        "deployment": "6089_old_gps2_diq202504-202509",
        "deployment_order": 18,
        "event_index": 72,
        "hour_of_day": 15.450555555555555,
        "media_type": "jpeg",
        "timestamp": "2024-09-22T15:27:02"
      },
      {
        "deployment": "6089_old_gps2_diq202504-202509",
        "deployment_order": 18,
        "event_index": 73,
        "hour_of_day": 15.455555555555556,
        "media_type": "mp4",
        "timestamp": "2024-09-22T15:27:20"
      },
      {
        "deployment": "6089_old_gps2_diq202504-202509",
        "deployment_order": 18,
        "event_index": 74,
        "hour_of_day": 21.191388888888888,
        "media_type": "jpeg",
        "timestamp": "2024-09-24T21:11:29"
      },
      {
        "deployment": "6089_old_gps2_diq202504-202509",
        "deployment_order": 18,
        "event_index": 75,
        "hour_of_day": 21.191666666666666,
        "media_type": "jpeg",
        "timestamp": "2024-09-24T21:11:30"
      },
      {
        "deployment": "6089_old_gps2_diq202504-202509",
        "deployment_order": 18,
        "event_index": 76,
        "hour_of_day": 1.5202777777777776,
        "media_type": "jpeg",
        "timestamp": "2024-09-25T01:31:13"
      },
      {
        "deployment": "6089_old_gps2_diq202504-202509",
        "deployment_order": 18,
        "event_index": 77,
        "hour_of_day": 1.5255555555555556,
        "media_type": "mp4",
        "timestamp": "2024-09-25T01:31:32"
      },
      {
        "deployment": "6089_old_gps2_diq202504-202509",
        "deployment_order": 18,
        "event_index": 78,
        "hour_of_day": 2.1075,
        "media_type": "jpeg",
        "timestamp": "2024-09-25T02:06:27"
      },
      {
        "deployment": "6089_old_gps2_diq202504-202509",
        "deployment_order": 18,
        "event_index": 79,
        "hour_of_day": 2.1077777777777778,
        "media_type": "jpeg",
        "timestamp": "2024-09-25T02:06:28"
      },
      {
        "deployment": "6089_old_gps2_diq202504-202509",
        "deployment_order": 18,
        "event_index": 80,
        "hour_of_day": 7.421111111111111,
        "media_type": "jpeg",
        "timestamp": "2024-09-25T07:25:16"
      },
      {
        "deployment": "6089_old_gps2_diq202504-202509",
        "deployment_order": 18,
        "event_index": 81,
        "hour_of_day": 8.825555555555555,
        "media_type": "jpeg",
        "timestamp": "2024-09-25T08:49:32"
      },
      {
        "deployment": "6089_old_gps2_diq202504-202509",
        "deployment_order": 18,
        "event_index": 82,
        "hour_of_day": 8.825833333333334,
        "media_type": "jpeg",
        "timestamp": "2024-09-25T08:49:33"
      },
      {
        "deployment": "6089_old_gps2_diq202504-202509",
        "deployment_order": 18,
        "event_index": 83,
        "hour_of_day": 8.831111111111111,
        "media_type": "mp4",
        "timestamp": "2024-09-25T08:49:52"
      },
      {
        "deployment": "6089_old_gps2_diq202504-202509",
        "deployment_order": 18,
        "event_index": 84,
        "hour_of_day": 8.834444444444445,
        "media_type": "jpeg",
        "timestamp": "2024-09-25T08:50:04"
      },
      {
        "deployment": "6089_old_gps2_diq202504-202509",
        "deployment_order": 18,
        "event_index": 85,
        "hour_of_day": 8.834722222222222,
        "media_type": "jpeg",
        "timestamp": "2024-09-25T08:50:05"
      },
      {
        "deployment": "6089_old_gps2_diq202504-202509",
        "deployment_order": 18,
        "event_index": 86,
        "hour_of_day": 8.84,
        "media_type": "mp4",
        "timestamp": "2024-09-25T08:50:24"
      },
      {
        "deployment": "6089_old_gps2_diq202504-202509",
        "deployment_order": 18,
        "event_index": 87,
        "hour_of_day": 8.842777777777778,
        "media_type": "jpeg",
        "timestamp": "2024-09-25T08:50:34"
      },
      {
        "deployment": "6089_old_gps2_diq202504-202509",
        "deployment_order": 18,
        "event_index": 88,
        "hour_of_day": 8.843055555555557,
        "media_type": "jpeg",
        "timestamp": "2024-09-25T08:50:35"
      },
      {
        "deployment": "6089_old_gps2_diq202504-202509",
        "deployment_order": 18,
        "event_index": 89,
        "hour_of_day": 8.848333333333334,
        "media_type": "mp4",
        "timestamp": "2024-09-25T08:50:54"
      },
      {
        "deployment": "6089_old_gps2_diq202504-202509",
        "deployment_order": 18,
        "event_index": 90,
        "hour_of_day": 23.951944444444443,
        "media_type": "jpeg",
        "timestamp": "2024-09-25T23:57:07"
      },
      {
        "deployment": "6089_old_gps2_diq202504-202509",
        "deployment_order": 18,
        "event_index": 91,
        "hour_of_day": 23.952222222222222,
        "media_type": "jpeg",
        "timestamp": "2024-09-25T23:57:08"
      },
      {
        "deployment": "6089_old_gps2_diq202504-202509",
        "deployment_order": 18,
        "event_index": 92,
        "hour_of_day": 23.95722222222222,
        "media_type": "mp4",
        "timestamp": "2024-09-25T23:57:26"
      },
      {
        "deployment": "6089_old_gps2_diq202504-202509",
        "deployment_order": 18,
        "event_index": 93,
        "hour_of_day": 0.16027777777777777,
        "media_type": "jpeg",
        "timestamp": "2024-09-26T00:09:37"
      },
      {
        "deployment": "6089_old_gps2_diq202504-202509",
        "deployment_order": 18,
        "event_index": 94,
        "hour_of_day": 0.16055555555555556,
        "media_type": "jpeg",
        "timestamp": "2024-09-26T00:09:38"
      },
      {
        "deployment": "6089_old_gps2_diq202504-202509",
        "deployment_order": 18,
        "event_index": 95,
        "hour_of_day": 0.16555555555555554,
        "media_type": "mp4",
        "timestamp": "2024-09-26T00:09:56"
      },
      {
        "deployment": "6089_old_gps2_diq202504-202509",
        "deployment_order": 18,
        "event_index": 96,
        "hour_of_day": 1.8575000000000002,
        "media_type": "jpeg",
        "timestamp": "2024-09-26T01:51:27"
      },
      {
        "deployment": "6089_old_gps2_diq202504-202509",
        "deployment_order": 18,
        "event_index": 97,
        "hour_of_day": 1.857777777777778,
        "media_type": "jpeg",
        "timestamp": "2024-09-26T01:51:28"
      },
      {
        "deployment": "6089_old_gps2_diq202504-202509",
        "deployment_order": 18,
        "event_index": 98,
        "hour_of_day": 1.8627777777777779,
        "media_type": "mp4",
        "timestamp": "2024-09-26T01:51:46"
      },
      {
        "deployment": "6089_old_gps2_diq202504-202509",
        "deployment_order": 18,
        "event_index": 99,
        "hour_of_day": 2.2894444444444444,
        "media_type": "jpeg",
        "timestamp": "2024-09-26T02:17:22"
      },
      {
        "deployment": "6089_old_gps2_diq202504-202509",
        "deployment_order": 18,
        "event_index": 100,
        "hour_of_day": 2.4855555555555555,
        "media_type": "mp4",
        "timestamp": "2024-09-26T02:29:08"
      },
      {
        "deployment": "6089_old_gps2_diq202504-202509",
        "deployment_order": 18,
        "event_index": 101,
        "hour_of_day": 7.034722222222222,
        "media_type": "jpeg",
        "timestamp": "2024-09-26T07:02:05"
      },
      {
        "deployment": "6089_old_gps2_diq202504-202509",
        "deployment_order": 18,
        "event_index": 102,
        "hour_of_day": 7.035,
        "media_type": "jpeg",
        "timestamp": "2024-09-26T07:02:06"
      },
      {
        "deployment": "6089_old_gps2_diq202504-202509",
        "deployment_order": 18,
        "event_index": 103,
        "hour_of_day": 7.04,
        "media_type": "mp4",
        "timestamp": "2024-09-26T07:02:24"
      },
      {
        "deployment": "6089_old_gps2_diq202504-202509",
        "deployment_order": 18,
        "event_index": 104,
        "hour_of_day": 7.055833333333333,
        "media_type": "jpeg",
        "timestamp": "2024-09-26T07:03:21"
      },
      {
        "deployment": "6089_old_gps2_diq202504-202509",
        "deployment_order": 18,
        "event_index": 105,
        "hour_of_day": 7.056111111111111,
        "media_type": "jpeg",
        "timestamp": "2024-09-26T07:03:22"
      },
      {
        "deployment": "6089_old_gps2_diq202504-202509",
        "deployment_order": 18,
        "event_index": 106,
        "hour_of_day": 7.061111111111111,
        "media_type": "mp4",
        "timestamp": "2024-09-26T07:03:40"
      },
      {
        "deployment": "6089_old_gps2_diq202504-202509",
        "deployment_order": 18,
        "event_index": 107,
        "hour_of_day": 7.065833333333333,
        "media_type": "jpeg",
        "timestamp": "2024-09-26T07:03:57"
      },
      {
        "deployment": "6089_old_gps2_diq202504-202509",
        "deployment_order": 18,
        "event_index": 108,
        "hour_of_day": 7.066111111111111,
        "media_type": "jpeg",
        "timestamp": "2024-09-26T07:03:58"
      },
      {
        "deployment": "6089_old_gps2_diq202504-202509",
        "deployment_order": 18,
        "event_index": 109,
        "hour_of_day": 7.071111111111111,
        "media_type": "mp4",
        "timestamp": "2024-09-26T07:04:16"
      },
      {
        "deployment": "6089_old_gps2_diq202504-202509",
        "deployment_order": 18,
        "event_index": 110,
        "hour_of_day": 7.0744444444444445,
        "media_type": "jpeg",
        "timestamp": "2024-09-26T07:04:28"
      },
      {
        "deployment": "6089_old_gps2_diq202504-202509",
        "deployment_order": 18,
        "event_index": 111,
        "hour_of_day": 7.074722222222222,
        "media_type": "jpeg",
        "timestamp": "2024-09-26T07:04:29"
      },
      {
        "deployment": "6089_old_gps2_diq202504-202509",
        "deployment_order": 18,
        "event_index": 112,
        "hour_of_day": 7.08,
        "media_type": "mp4",
        "timestamp": "2024-09-26T07:04:48"
      },
      {
        "deployment": "6089_old_gps2_diq202504-202509",
        "deployment_order": 18,
        "event_index": 113,
        "hour_of_day": 7.084444444444444,
        "media_type": "jpeg",
        "timestamp": "2024-09-26T07:05:04"
      },
      {
        "deployment": "6089_old_gps2_diq202504-202509",
        "deployment_order": 18,
        "event_index": 114,
        "hour_of_day": 7.084722222222222,
        "media_type": "jpeg",
        "timestamp": "2024-09-26T07:05:05"
      },
      {
        "deployment": "6089_old_gps2_diq202504-202509",
        "deployment_order": 18,
        "event_index": 115,
        "hour_of_day": 7.09,
        "media_type": "mp4",
        "timestamp": "2024-09-26T07:05:24"
      },
      {
        "deployment": "6089_old_gps2_diq202504-202509",
        "deployment_order": 18,
        "event_index": 116,
        "hour_of_day": 7.111666666666666,
        "media_type": "jpeg",
        "timestamp": "2024-09-26T07:06:42"
      },
      {
        "deployment": "6089_old_gps2_diq202504-202509",
        "deployment_order": 18,
        "event_index": 117,
        "hour_of_day": 8.96361111111111,
        "media_type": "jpeg",
        "timestamp": "2024-09-26T08:57:49"
      },
      {
        "deployment": "6089_old_gps2_diq202504-202509",
        "deployment_order": 18,
        "event_index": 118,
        "hour_of_day": 0.21083333333333334,
        "media_type": "jpeg",
        "timestamp": "2024-09-27T00:12:39"
      },
      {
        "deployment": "6089_old_gps2_diq202504-202509",
        "deployment_order": 18,
        "event_index": 119,
        "hour_of_day": 0.2111111111111111,
        "media_type": "jpeg",
        "timestamp": "2024-09-27T00:12:40"
      },
      {
        "deployment": "6089_old_gps2_diq202504-202509",
        "deployment_order": 18,
        "event_index": 120,
        "hour_of_day": 0.21611111111111111,
        "media_type": "mp4",
        "timestamp": "2024-09-27T00:12:58"
      },
      {
        "deployment": "6089_old_gps2_diq202504-202509",
        "deployment_order": 18,
        "event_index": 121,
        "hour_of_day": 23.747222222222224,
        "media_type": "jpeg",
        "timestamp": "2024-09-28T23:44:50"
      },
      {
        "deployment": "6089_old_gps2_diq202504-202509",
        "deployment_order": 18,
        "event_index": 122,
        "hour_of_day": 23.747500000000002,
        "media_type": "jpeg",
        "timestamp": "2024-09-28T23:44:51"
      },
      {
        "deployment": "6089_old_gps2_diq202504-202509",
        "deployment_order": 18,
        "event_index": 123,
        "hour_of_day": 23.752777777777776,
        "media_type": "mp4",
        "timestamp": "2024-09-28T23:45:10"
      },
      {
        "deployment": "6089_old_gps2_diq202504-202509",
        "deployment_order": 18,
        "event_index": 124,
        "hour_of_day": 7.338611111111111,
        "media_type": "jpeg",
        "timestamp": "2024-09-29T07:20:19"
      },
      {
        "deployment": "6089_old_gps2_diq202504-202509",
        "deployment_order": 18,
        "event_index": 125,
        "hour_of_day": 7.3438888888888885,
        "media_type": "mp4",
        "timestamp": "2024-09-29T07:20:38"
      },
      {
        "deployment": "6089_old_gps2_diq202504-202509",
        "deployment_order": 18,
        "event_index": 126,
        "hour_of_day": 8.276666666666667,
        "media_type": "jpeg",
        "timestamp": "2024-09-29T08:16:36"
      },
      {
        "deployment": "6089_old_gps2_diq202504-202509",
        "deployment_order": 18,
        "event_index": 127,
        "hour_of_day": 8.276944444444446,
        "media_type": "jpeg",
        "timestamp": "2024-09-29T08:16:37"
      },
      {
        "deployment": "6089_old_gps2_diq202504-202509",
        "deployment_order": 18,
        "event_index": 128,
        "hour_of_day": 9.431388888888888,
        "media_type": "jpeg",
        "timestamp": "2024-09-29T09:25:53"
      },
      {
        "deployment": "6089_old_gps2_diq202504-202509",
        "deployment_order": 18,
        "event_index": 129,
        "hour_of_day": 2.6222222222222222,
        "media_type": "jpeg",
        "timestamp": "2024-09-30T02:37:20"
      },
      {
        "deployment": "6089_old_gps2_diq202504-202509",
        "deployment_order": 18,
        "event_index": 130,
        "hour_of_day": 2.6225,
        "media_type": "jpeg",
        "timestamp": "2024-09-30T02:37:21"
      },
      {
        "deployment": "6089_old_gps2_diq202504-202509",
        "deployment_order": 18,
        "event_index": 131,
        "hour_of_day": 2.6277777777777778,
        "media_type": "mp4",
        "timestamp": "2024-09-30T02:37:40"
      },
      {
        "deployment": "6089_old_gps2_diq202504-202509",
        "deployment_order": 18,
        "event_index": 132,
        "hour_of_day": 7.403333333333333,
        "media_type": "jpeg",
        "timestamp": "2024-09-30T07:24:12"
      },
      {
        "deployment": "6089_old_gps2_diq202504-202509",
        "deployment_order": 18,
        "event_index": 133,
        "hour_of_day": 7.403611111111111,
        "media_type": "jpeg",
        "timestamp": "2024-09-30T07:24:13"
      },
      {
        "deployment": "6089_old_gps2_diq202504-202509",
        "deployment_order": 18,
        "event_index": 134,
        "hour_of_day": 7.408888888888889,
        "media_type": "mp4",
        "timestamp": "2024-09-30T07:24:32"
      },
      {
        "deployment": "6089_old_gps2_diq202504-202509",
        "deployment_order": 18,
        "event_index": 135,
        "hour_of_day": 7.4125000000000005,
        "media_type": "jpeg",
        "timestamp": "2024-09-30T07:24:45"
      },
      {
        "deployment": "6089_old_gps2_diq202504-202509",
        "deployment_order": 18,
        "event_index": 136,
        "hour_of_day": 7.412777777777778,
        "media_type": "jpeg",
        "timestamp": "2024-09-30T07:24:46"
      },
      {
        "deployment": "6089_old_gps2_diq202504-202509",
        "deployment_order": 18,
        "event_index": 137,
        "hour_of_day": 7.417777777777778,
        "media_type": "mp4",
        "timestamp": "2024-09-30T07:25:04"
      },
      {
        "deployment": "6089_old_gps2_diq202504-202509",
        "deployment_order": 18,
        "event_index": 138,
        "hour_of_day": 7.536111111111111,
        "media_type": "jpeg",
        "timestamp": "2024-09-30T07:32:10"
      },
      {
        "deployment": "6089_old_gps2_diq202504-202509",
        "deployment_order": 18,
        "event_index": 139,
        "hour_of_day": 7.536388888888888,
        "media_type": "jpeg",
        "timestamp": "2024-09-30T07:32:11"
      },
      {
        "deployment": "6089_old_gps2_diq202504-202509",
        "deployment_order": 18,
        "event_index": 140,
        "hour_of_day": 7.541666666666667,
        "media_type": "mp4",
        "timestamp": "2024-09-30T07:32:30"
      },
      {
        "deployment": "6089_old_gps2_diq202504-202509",
        "deployment_order": 18,
        "event_index": 141,
        "hour_of_day": 17.596944444444443,
        "media_type": "jpeg",
        "timestamp": "2024-09-30T17:35:49"
      },
      {
        "deployment": "6089_old_gps2_diq202504-202509",
        "deployment_order": 18,
        "event_index": 142,
        "hour_of_day": 17.59722222222222,
        "media_type": "jpeg",
        "timestamp": "2024-09-30T17:35:50"
      },
      {
        "deployment": "6089_old_gps2_diq202504-202509",
        "deployment_order": 18,
        "event_index": 143,
        "hour_of_day": 17.602222222222224,
        "media_type": "mp4",
        "timestamp": "2024-09-30T17:36:08"
      },
      {
        "deployment": "6089_old_gps2_diq202504-202509",
        "deployment_order": 18,
        "event_index": 144,
        "hour_of_day": 19.490833333333335,
        "media_type": "jpeg",
        "timestamp": "2024-09-30T19:29:27"
      },
      {
        "deployment": "6089_old_gps2_diq202504-202509",
        "deployment_order": 18,
        "event_index": 145,
        "hour_of_day": 19.491111111111113,
        "media_type": "jpeg",
        "timestamp": "2024-09-30T19:29:28"
      },
      {
        "deployment": "6089_old_gps2_diq202504-202509",
        "deployment_order": 18,
        "event_index": 146,
        "hour_of_day": 19.496111111111112,
        "media_type": "mp4",
        "timestamp": "2024-09-30T19:29:46"
      },
      {
        "deployment": "6089_old_gps2_diq202504-202509",
        "deployment_order": 18,
        "event_index": 147,
        "hour_of_day": 8.746944444444443,
        "media_type": "jpeg",
        "timestamp": "2024-10-02T08:44:49"
      },
      {
        "deployment": "6089_old_gps2_diq202504-202509",
        "deployment_order": 18,
        "event_index": 148,
        "hour_of_day": 8.747222222222222,
        "media_type": "jpeg",
        "timestamp": "2024-10-02T08:44:50"
      },
      {
        "deployment": "6089_old_gps2_diq202504-202509",
        "deployment_order": 18,
        "event_index": 149,
        "hour_of_day": 8.752222222222223,
        "media_type": "mp4",
        "timestamp": "2024-10-02T08:45:08"
      },
      {
        "deployment": "6089_old_gps2_diq202504-202509",
        "deployment_order": 18,
        "event_index": 150,
        "hour_of_day": 8.804444444444446,
        "media_type": "jpeg",
        "timestamp": "2024-10-02T08:48:16"
      },
      {
        "deployment": "6089_old_gps2_diq202504-202509",
        "deployment_order": 18,
        "event_index": 151,
        "hour_of_day": 8.804722222222223,
        "media_type": "jpeg",
        "timestamp": "2024-10-02T08:48:17"
      },
      {
        "deployment": "6089_old_gps2_diq202504-202509",
        "deployment_order": 18,
        "event_index": 152,
        "hour_of_day": 10.025,
        "media_type": "jpeg",
        "timestamp": "2024-10-02T10:01:30"
      },
      {
        "deployment": "6089_old_gps2_diq202504-202509",
        "deployment_order": 18,
        "event_index": 153,
        "hour_of_day": 10.025277777777779,
        "media_type": "jpeg",
        "timestamp": "2024-10-02T10:01:31"
      },
      {
        "deployment": "6089_old_gps2_diq202504-202509",
        "deployment_order": 18,
        "event_index": 154,
        "hour_of_day": 10.030555555555557,
        "media_type": "mp4",
        "timestamp": "2024-10-02T10:01:50"
      },
      {
        "deployment": "6089_old_gps2_diq202504-202509",
        "deployment_order": 18,
        "event_index": 155,
        "hour_of_day": 23.369444444444444,
        "media_type": "mp4",
        "timestamp": "2024-10-02T23:22:10"
      }
    ]
  },
  "encoding": {
    "color": {
      "field": "media_type",
      "scale": {
        "scheme": "tableau10"
      },
      "title": "Media type",
      "type": "nominal"
    },
    "shape": {
      "field": "media_type",
      "title": "Media type",
      "type": "nominal"
    },
    "tooltip": [
      {
        "field": "deployment",
        "title": "Deployment",
        "type": "nominal"
      },
      {
        "field": "timestamp",
        "format": "%Y-%m-%d %H:%M:%S",
        "title": "Timestamp",
        "type": "temporal"
      },
      {
        "field": "hour_of_day",
        "format": ".2f",
        "title": "Hour of day",
        "type": "quantitative"
      },
      {
        "field": "media_type",
        "title": "Media type",
        "type": "nominal"
      }
    ],
    "x": {
      "field": "timestamp",
      "title": "Timestamp",
      "type": "temporal"
    },
    "y": {
      "field": "hour_of_day",
      "scale": {
        "domain": [
          0,
          24
        ]
      },
      "title": "Hour of day",
      "type": "quantitative"
    }
  },
  "height": 460,
  "mark": {
    "opacity": 0.78,
    "size": 46,
    "type": "circle"
  },
  "params": [
    {
      "bind": "scales",
      "name": "param_1e9efca18e7a2868",
      "select": {
        "encodings": [
          "x",
          "y"
        ],
        "type": "interval"
      }
    }
  ],
  "title": "Deployment detail: 6089_old_gps2_diq202504-202509",
  "width": 1180
}
